{"inkVersion":19,"root":[[{"->":"second_story"},["done",{"#f":7,"#n":"g-0"}],null],"done",{"second_story":[["ev",{"VAR?":"first_discussion_passed"},1,"==","/ev",{"->":".^.b","c":true},{"b":["\n",{"->":".^.^.^.second_discussion"},{"->":".^.^.^.2"},null]}],["ev",{"VAR?":"first_discussion_passed"},0,"==","/ev",{"->":".^.b","c":true},{"b":["\n",{"->":".^.^.^.first_discussion"},{"->":".^.^.^.2"},null]}],"nop","\n",{"first_discussion":[["^How are you Antonio? ",{"#":"player"},"\n","^Nothing new, you're still working on Lotto's death? ",{"#":"otherCharacter"},"\n",["ev",{"^->":"second_story.first_discussion.0.6.$r1"},{"temp=":"$r"},"str",{"->":".^.s"},[{"#n":"$r1"}],"/str","/ev",{"*":".^.^.c-0","flg":2},{"s":["^I'm stuck... ",{"->":"$r","var":true},null]}],["ev",{"^->":"second_story.first_discussion.0.7.$r1"},{"temp=":"$r"},"str",{"->":".^.s"},[{"#n":"$r1"}],"/str","/ev",{"*":".^.^.c-1","flg":18},{"s":["^Do you know that? ",{"->":"$r","var":true},null]}],{"c-0":["ev",{"^->":"second_story.first_discussion.0.c-0.$r2"},"/ev",{"temp=":"$r"},{"->":".^.^.6.s"},[{"#n":"$r2"}],{"#":"player"},"\n","^Don't give a fuck ",{"#":"otherCharacter"},"\n",{"->":".^.^.g-0"},{"#f":7}],"c-1":["ev",{"^->":"second_story.first_discussion.0.c-1.$r2"},"/ev",{"temp=":"$r"},{"->":".^.^.7.s"},[{"#n":"$r2"}],{"#":"player"},"\n","^Maybe... Kidding, of course I know. Come see me later ",{"#":"otherCharacter"},"\n","ev",1,"/ev",{"VAR=":"first_discussion_passed","re":true},{"->":".^.^.g-0"},{"#f":7}],"g-0":["^Now get the fuck out. ",{"#":"otherCharacter"},"\n","ev","str","^Continue?","/str","/ev",{"*":".^.c-2","flg":4},"ev","str","^Quit?","/str","/ev",{"*":".^.c-3","flg":20},{"c-2":["\n",{"->":".^.^.^.^.^"},{"#f":7}],"c-3":["\n","end",{"#f":7}],"#f":7}]}],{"#f":3}],"second_discussion":["^TADADADA ",{"#":"otherCharacter"},"\n","end",{"#f":3}],"#f":3}],"global decl":["ev",0,{"VAR=":"first_discussion_passed"},"/ev","end",null],"#f":3}],"listDefs":{}}